watchgod/__init__.py
watchgod/__main__.py
watchgod/cli.py
watchgod/main.py
watchgod/py.typed
watchgod/version.py
watchgod/watcher.py
watchgod-0.8.2.dist-info/LICENSE
watchgod-0.8.2.dist-info/METADATA
watchgod-0.8.2.dist-info/WHEEL
watchgod-0.8.2.dist-info/entry_points.txt
watchgod-0.8.2.dist-info/top_level.txt
watchgod-0.8.2.dist-info/zip-safe
watchgod-0.8.2.dist-info/RECORD
