Metadata-Version: 2.1
Name: watchgod
Version: 0.8.2
Summary: Simple, modern file watching and code reload in python.
Home-page: https://github.com/samuelcolvin/watchfiles
Author: Samuel Colvin
Author-email: s@muelcolvin.com
License: MIT
Platform: UNKNOWN
Classifier: Development Status :: 7 - Inactive
Classifier: Environment :: Console
Classifier: Programming Language :: Python
Classifier: Programming Language :: Python :: 3
Classifier: Programming Language :: Python :: 3 :: Only
Classifier: Programming Language :: Python :: 3.7
Classifier: Programming Language :: Python :: 3.8
Classifier: Programming Language :: Python :: 3.9
Classifier: Programming Language :: Python :: 3.10
Classifier: Intended Audience :: Developers
Classifier: Intended Audience :: Information Technology
Classifier: Intended Audience :: System Administrators
Classifier: License :: OSI Approved :: MIT License
Classifier: Operating System :: POSIX :: Linux
Classifier: Operating System :: Microsoft :: Windows
Classifier: Operating System :: MacOS
Classifier: Environment :: MacOS X
Classifier: Topic :: Software Development :: Libraries :: Python Modules
Classifier: Topic :: System :: Filesystems
Classifier: Framework :: AnyIO
Requires-Python: >=3.7
License-File: LICENSE
